pyqsar/__init__.py
pyqsar/classification.py
pyqsar/clustering.py
pyqsar/cook_sdf.py
pyqsar/cross_validation.py
pyqsar/data_tools.py
pyqsar/draw_mol.py
pyqsar/export_model.py
pyqsar/feature_selection_multi.py
pyqsar/feature_selection_single.py
pyqsar-1.3.dist-info/METADATA
pyqsar-1.3.dist-info/WHEEL
pyqsar-1.3.dist-info/top_level.txt
pyqsar-1.3.dist-info/RECORD
