Metadata-Version: 2.1
Name: pyqsar
Version: 1.3
Summary: Feature selection & QSAR modeling package
Home-page: https://github.com/crong-k/pyqsar_tutorial
Author: Sinyoung
Author-email: crong24601@gmail.com
License: MIT License
Keywords: QSAR,feature selection,machine learning
Platform: UNKNOWN
Classifier: Development Status :: 3 - Alpha
Classifier: Intended Audience :: Developers
Classifier: Programming Language :: Python :: 2.7
Classifier: License :: OSI Approved :: MIT License
Requires-Dist: numpy (>=1.12.0)
Requires-Dist: setuptools (>=27.2.0)
Requires-Dist: pandas (>=0.24.2)
Requires-Dist: scikit-learn (>=0.18.1)
Requires-Dist: matplotlib (>=2.0.2)
Requires-Dist: ipywidgets (>=6.0.0)
Requires-Dist: ipython (>=5.3.0)
Requires-Dist: bokeh (>=0.12.5)
Requires-Dist: joblib (>=0.11)
